{
  "ARDUINO_SKETCH_PATH": "/home/pi/Arduino/TS1_Sensor/TS1_Sensor.ino",
  "WEBHOOK_URL": "https://n8n.ts1cloud.com/webhook/your-webhook-id",
  "SUCCESS_WEBHOOK_URL": "https://n8n.ts1cloud.com/webhook/success-notification",
  "SERIAL_LINE_NUMBER": 137,
  "COM_PORT": "/dev/ttyUSB0",
  "BAUD_RATE": "115200",
  "PRINTER_COM_PORT": "/dev/ttyUSB1",
  "PRINTER_BAUD_RATE": "115200",
  "PCB_GRID_X": 30,
  "PCB_GRID_Y": 110,
  "PCB_ROWS": 2,
  "PCB_COLS": 5,
  "PCB_START_X": 0,
  "PCB_START_Y": 0,
  "PCB_Z_UP": 10,
  "PCB_Z_DOWN": 0
} 